{"inkVersion":21,"root":[[{"->":"main"},["done",{"#f":5,"#n":"g-0"}],null],"done",{"main":[["^Oh, you're here! And awake! I narrowly escaped a monster back there.","\n","^Be careful, the forest ahead is teeming with harpies.","\n","^Let me heal you up.","\n","ev","str","^Thankyou!","/str","/ev",{"*":".^.c-0","flg":4},"ev","str","^What were you doing out here?","/str","/ev",{"*":".^.c-1","flg":4},{"c-0":["\n",{"->":"thankyouReply"},{"#f":5}],"c-1":["\n",{"->":"whatIWasDoing"},{"#f":5}]}],{"#f":1}],"thankyouReply":["^Your welcome, I was out looking for -Ionized Ether Crystals- which are a rare drop from the harpies in this area.","\n","^I was wanting to try an experiment with them.","\n","^If you feel up to it could you try to round some up for me?","\n","^In the meantime I'm going to head back and set up my tent, Ill be there if you need me.","\n","end",{"#f":1}],"whatIWasDoing":["^I was out looking for -Ionized Ether Crystals- for my research project.","\n","^Apparently the harpies sometimes drop them and I could use a few more.","\n","^I should get back to the island and set up my tent, you know where to find me.","\n","end",{"#f":1}],"#f":1}],"listDefs":{}}